dsnd-probability-10/Binomialdistribution.py
dsnd-probability-10/Gaussiandistribution.py
dsnd-probability-10/Generaldistribution.py
dsnd-probability-10/__init__.py
dsnd_probability_nim/Binomialdistribution.py
dsnd_probability_nim/Gaussiandistribution.py
dsnd_probability_nim/Generaldistribution.py
dsnd_probability_nim/__init__.py
dsnd_probability_nim-1.0.dist-info/METADATA
dsnd_probability_nim-1.0.dist-info/WHEEL
dsnd_probability_nim-1.0.dist-info/top_level.txt
dsnd_probability_nim-1.0.dist-info/RECORD
