Metadata-Version: 2.1
Name: dsnd-probability-nim
Version: 1.0
Summary: Gaussian and Binomial distributions
Home-page: UNKNOWN
Author: Nimrod Michaeli
Author-email: nimrodmic@gmail.com
License: UNKNOWN
Platform: UNKNOWN
